modelcluster/__init__.py
modelcluster/datetime_utils.py
modelcluster/fields.py
modelcluster/forms.py
modelcluster/models.py
modelcluster/queryset.py
modelcluster/tags.py
modelcluster/utils.py
modelcluster/contrib/__init__.py
modelcluster/contrib/taggit.py
django_modelcluster-6.4.dist-info/LICENSE
django_modelcluster-6.4.dist-info/METADATA
django_modelcluster-6.4.dist-info/WHEEL
django_modelcluster-6.4.dist-info/top_level.txt
django_modelcluster-6.4.dist-info/RECORD
