Metadata-Version: 2.1
Name: django-modelcluster
Version: 6.4
Summary: Django extension to allow working with 'clusters' of models as a single unit, independently of the database
Home-page: https://github.com/wagtail/django-modelcluster
Author: Matthew Westcott
Author-email: matthew.westcott@torchbox.com
License: BSD
Classifier: Development Status :: 5 - Production/Stable
Classifier: Environment :: Web Environment
Classifier: Intended Audience :: Developers
Classifier: License :: OSI Approved :: BSD License
Classifier: Operating System :: OS Independent
Classifier: Programming Language :: Python
Classifier: Programming Language :: Python :: 3
Classifier: Programming Language :: Python :: 3.9
Classifier: Programming Language :: Python :: 3.10
Classifier: Programming Language :: Python :: 3.11
Classifier: Programming Language :: Python :: 3.12
Classifier: Programming Language :: Python :: 3.13
Classifier: Programming Language :: Python :: 3 :: Only
Classifier: Framework :: Django
Requires-Python: >=3.9
Provides-Extra: taggit
License-File: LICENSE
